togai_my_packaging/__init__.py
togai_my_packaging/cities.json
togai_my_packaging/my_file.py
togai_my_packaging/my_other_file.py
togai_my_packaging/states_info.py
togai_my_packaging/my_folder/__init__.py
togai_my_packaging/my_folder/cities.json
togai_my_packaging/my_folder/my_nested_file.py
togai_my_packaging-0.0.11.dist-info/METADATA
togai_my_packaging-0.0.11.dist-info/WHEEL
togai_my_packaging-0.0.11.dist-info/top_level.txt
togai_my_packaging-0.0.11.dist-info/RECORD
