Metadata-Version: 2.4
Name: togai-my-packaging
Version: 0.0.11
Summary: demo package
Author: Togay Tunca
Author-email: ttunca@evin-ai.com
Maintainer-email: Togay Tunca <ttunca@evin-ai.com>
License-Expression: MIT
Keywords: package,python-packaging
Classifier: Development Status :: 3 - Alpha
Classifier: Intended Audience :: Developers
Classifier: Topic :: Software Development :: Build Tools
Classifier: Programming Language :: Python :: 3
Classifier: Programming Language :: Python :: 3.9
Classifier: Programming Language :: Python :: 3.10
Classifier: Programming Language :: Python :: 3.11
Classifier: Programming Language :: Python :: 3.12
Classifier: Programming Language :: Python :: 3.13
Classifier: Programming Language :: Python :: 3 :: Only
Requires-Python: >=3.9
Requires-Dist: numpy
Provides-Extra: test
Requires-Dist: pytest; extra == "test"
Requires-Dist: pytest-cov; extra == "test"
Provides-Extra: release
Requires-Dist: build; extra == "release"
Requires-Dist: twine; extra == "release"
Provides-Extra: static-code-qa
Requires-Dist: pre-commit; extra == "static-code-qa"
Provides-Extra: dev
Requires-Dist: pytest; extra == "dev"
Requires-Dist: pytest-cov; extra == "dev"
Requires-Dist: build; extra == "dev"
Requires-Dist: twine; extra == "dev"
Requires-Dist: pre-commit; extra == "dev"
